setup.py
Circle_Tickler.egg-info/PKG-INFO
Circle_Tickler.egg-info/SOURCES.txt
Circle_Tickler.egg-info/dependency_links.txt
Circle_Tickler.egg-info/entry_points.txt
Circle_Tickler.egg-info/requires.txt
Circle_Tickler.egg-info/top_level.txt
tickle_circle/__init__.py