Metadata-Version: 1.0
Name: Circle-Tickler
Version: 1.0.1
Summary: ...
Home-page: https://github.com/migurski/circle-tickler
Author: Michal Migurski
Author-email: mike-github@teczno.com
License: UNKNOWN
Platform: UNKNOWN
